fryers/__init__.py
fryers/fyers.py
fryers-1.0.0.dist-info/LICENSE
fryers-1.0.0.dist-info/METADATA
fryers-1.0.0.dist-info/WHEEL
fryers-1.0.0.dist-info/top_level.txt
fryers-1.0.0.dist-info/RECORD
