Metadata-Version: 2.1
Name: fryers
Version: 1.0.0
Summary: A wrapper around fyers_apiv3 to make it easier to use
Author-email: shoaib wani <wanishoaib@protonmail.com>
License: MIT
Project-URL: Homepage, https://github.com/pyloris/Fryers
Keywords: fyers,fyers-api,trading,fyers_apiv3
Classifier: Intended Audience :: Financial and Insurance Industry
Classifier: License :: OSI Approved :: MIT License
Classifier: Operating System :: OS Independent
Classifier: Programming Language :: Python :: 3.11
Classifier: Topic :: Utilities
Requires-Python: >=3.11
License-File: LICENSE
Requires-Dist: fyers-apiv3
Requires-Dist: pycryptodome
Requires-Dist: termcolor
Requires-Dist: requests
Requires-Dist: pandas
